[[{"titulo": "Trabajadores protegidos por el Seguro de Ley sobre accidentes o enfermedad profesional", "Fuente": " Superintendencia de Seguridad Social", "LinkDatosOriginales": "https://smartdata-demo.sfo2.digitaloceanspaces.com/data/seguridad.xlsx", "comment": "Empresas adherentes al Seguro de Ley sobre accidentes o enfermedad profesional. Fuente: Superintendencia de Seguridad Social", "linkPlot": "https://smartdata-demo.sfo2.digitaloceanspaces.com/data/img/Seg_02_Trabajadadores_protegidos.png", "glosario": ""}], [{"anio": 2018, "regiones": {"PAIS": {"meses": {"Ene": {"Construccion": 643086, "tooltip": {"Construccion": 643086, "Fecha: ": "2018/ Ene", "Participación": "10.6%"}}, "Feb": {"Construccion": 637822, "tooltip": {"Construccion": 637822, "Fecha: ": "2018/ Feb", "Participación": "10.6%"}}, "Mar": {"Construccion": 645912, "tooltip": {"Construccion": 645912, "Fecha: ": "2018/ Mar", "Participación": "10.7%"}}, "Abr": {"Construccion": 636578, "tooltip": {"Construccion": 636578, "Fecha: ": "2018/ Abr", "Participación": "10.7%"}}, "May": {"Construccion": 657910, "tooltip": {"Construccion": 657910, "Fecha: ": "2018/ May", "Participación": "10.9%"}}, "Jun": {"Construccion": 657716, "tooltip": {"Construccion": 657716, "Fecha: ": "2018/ Jun", "Participación": "10.9%"}}, "Jul": {"Construccion": 657838, "tooltip": {"Construccion": 657838, "Fecha: ": "2018/ Jul", "Participación": "10.9%"}}, "Ago": {"Construccion": 667738, "tooltip": {"Construccion": 667738, "Fecha: ": "2018/ Ago", "Participación": "11%"}}, "Sep": {"Construccion": 655646, "tooltip": {"Construccion": 655646, "Fecha: ": "2018/ Sep", "Participación": "10.8%"}}, "Oct": {"Construccion": 680658, "tooltip": {"Construccion": 680658, "Fecha: ": "2018/ Oct", "Participación": "11.1%"}}, "Nov": {"Construccion": 696748, "tooltip": {"Construccion": 696748, "Fecha: ": "2018/ Nov", "Participación": "11.1%"}}}}}}]]
