[[{"titulo": "Trabajadores protegidos por el Seguro de Ley sobre accidentes o enfermedad profesional por región", "Fuente": "Superintendencia de Seguridad Social y pruebita", "LinkDatosOriginales": "https://smartdata-demo.sfo2.digitaloceanspaces.com/data/seguridad.xlsx", "comment": "Trabajadores protegidos por el Seguro de Ley sobre accidentes o enfermedad profesional por región. Fuente Superintendencia de Seguridad Social", "linkPlot": "https://smartdata-demo.sfo2.digitaloceanspaces.com/data/img/Seg_03_Trabajadadores_protegidos_porRegion.png", "glosario": ""}], [{"anio": 2018, "regiones": {"De Arica y Parinacota": {"meses": {".": {"De Arica y Parinacota": 2459.3, "tooltip": {"De Arica y Parinacota": 2459.3, "Fecha: ": "2015/ .", "Participación": "0.4%"}}}}, "De Tarapacá": {"meses": {".": {"De Tarapacá": 10250.7, "tooltip": {"De Tarapacá": 10250.7, "Fecha: ": "2015/ .", "Participación": "1.6%"}}}}, "De Antofagasta": {"meses": {".": {"De Antofagasta": 24317.0, "tooltip": {"De Antofagasta": 24317.0, "Fecha: ": "2015/ .", "Participación": "3.9%"}}}}, "De Atacama": {"meses": {".": {"De Atacama": 9563.3, "tooltip": {"De Atacama": 9563.3, "Fecha: ": "2015/ .", "Participación": "1.5%"}}}}, "De Coquimbo": {"meses": {".": {"De Coquimbo": 17565.7, "tooltip": {"De Coquimbo": 17565.7, "Fecha: ": "2015/ .", "Participación": "2.8%"}}}}, "De Valparaíso": {"meses": {".": {"De Valparaíso": 40102.5, "tooltip": {"De Valparaíso": 40102.5, "Fecha: ": "2015/ .", "Participación": "6.4%"}}}}, "Del Libertador Gral. Bdo. O'Higgins": {"meses": {".": {"Del Libertador Gral. Bdo. O'Higgins": 15367.0, "tooltip": {"Del Libertador Gral. Bdo. O'Higgins": 15367.0, "Fecha: ": "2015/ .", "Participación": "2.4%"}}}}, "Del Maule": {"meses": {".": {"Del Maule": 16800.0, "tooltip": {"Del Maule": 16800.0, "Fecha: ": "2015/ .", "Participación": "2.7%"}}}}, "De Ñuble": {"meses": {".": {"De Ñuble": 0, "tooltip": {"De Ñuble": 0, "Fecha: ": "2015/ .", "Participación": "0%"}}}}, "Del Biobío": {"meses": {".": {"Del Biobío": 46875.2, "tooltip": {"Del Biobío": 46875.2, "Fecha: ": "2015/ .", "Participación": "7.4%"}}}}, "De La Araucanía": {"meses": {".": {"De La Araucanía": 27386.4, "tooltip": {"De La Araucanía": 27386.4, "Fecha: ": "2015/ .", "Participación": "4.3%"}}}}, "De Los Ríos": {"meses": {".": {"De Los Ríos": 6068.7, "tooltip": {"De Los Ríos": 6068.7, "Fecha: ": "2015/ .", "Participación": "1%"}}}}, "De Los Lagos": {"meses": {".": {"De Los Lagos": 18264.7, "tooltip": {"De Los Lagos": 18264.7, "Fecha: ": "2015/ .", "Participación": "2.9%"}}}}, "Aysén del Gral. Carlos Ibañez del Campo": {"meses": {".": {"Aysén del Gral. Carlos Ibañez del Campo": 2245.1, "tooltip": {"Aysén del Gral. Carlos Ibañez del Campo": 2245.1, "Fecha: ": "2015/ .", "Participación": "0.4%"}}}}, "De Magallanes y la Antártica Chilena": {"meses": {".": {"De Magallanes y la Antártica Chilena": 3700.8, "tooltip": {"De Magallanes y la Antártica Chilena": 3700.8, "Fecha: ": "2015/ .", "Participación": "0.6%"}}}}, "Metropolitana de Santiago": {"meses": {".": {"Metropolitana de Santiago": 389383.0, "tooltip": {"Metropolitana de Santiago": 389383.0, "Fecha: ": "2015/ .", "Participación": "61.8%"}}}}}}]]
